fastdocx/__init__.py
fastdocx/core.py
fastdocx/download.py
fastdocx/engine.py
fastdocx/reader.py
fastdocx/writer.py
fastdocx/ui/__init__.py
fastdocx/ui/form.py
fastdocx/ui/style.py
fastdocx/ui/ui.py
fastdocx-0.2.2.dist-info/LICENSE
fastdocx-0.2.2.dist-info/METADATA
fastdocx-0.2.2.dist-info/WHEEL
fastdocx-0.2.2.dist-info/top_level.txt
fastdocx-0.2.2.dist-info/RECORD
