Metadata-Version: 2.1
Name: fastdocx
Version: 0.2.2
Summary: use template to gen word everywhere
Home-page: https://github.com/SOVLOOKUP/FastDocx
Author: sovlookup
Author-email: gonorth@qq.com
License: UNKNOWN
Platform: UNKNOWN
Classifier: Programming Language :: Python :: 3
Classifier: License :: OSI Approved :: MIT License
Classifier: Operating System :: OS Independent
Requires-Python: >=3.7
Requires-Dist: python-docx
Requires-Dist: trio
Requires-Dist: httpx
Requires-Dist: tqdm
Requires-Dist: PyQt5
